[
  {
    "unit": "Barded Warhorse",
    "M": 7,
    "WS": 3,
    "BS": null,
    "S": 3,
    "T": null,
    "W": null,
    "I": 3,
    "A": 1,
    "Ld": null,
    "type": "Heavy Cavalry"
  },
  {
    "unit": "Captain of the Empire",
    "M": 4,
    "WS": 5,
    "BS": 5,
    "S": 4,
    "T": 4,
    "W": 2,
    "I": 4,
    "A": 2,
    "Ld": 9,
    "type": "Regular Infantry, Character"
  },
  {
    "unit": "Demigryph Knight",
    "M": null,
    "WS": 4,
    "BS": 3,
    "S": 4,
    "T": 4,
    "W": 3,
    "I": 4,
    "A": 1,
    "Ld": 8,
    "type": "Monstrous Cavalry"
  },
  {
    "unit": "Empire Engineer",
    "M": 4,
    "WS": 3,
    "BS": 4,
    "S": 3,
    "T": 3,
    "W": 2,
    "I": 3,
    "A": 1,
    "Ld": 7,
    "type": "Regular Infantry, Character"
  },
  {
    "unit": "Greatsword",
    "M": 4,
    "WS": 4,
    "BS": 3,
    "S": 4,
    "T": 3,
    "W": 1,
    "I": 3,
    "A": 1,
    "Ld": 8,
    "type": "Regular Infantry"
  },
  {
    "unit": "Empire Knight",
    "M": null,
    "WS": 4,
    "BS": 3,
    "S": 3,
    "T": 3,
    "W": 1,
    "I": 3,
    "A": 1,
    "Ld": 8,
    "type": "Heavy Cavalry"
  },
  {
    "unit": "Steam Tank",
    "M": 4,
    "WS": null,
    "BS": null,
    "S": 6,
    "T": 7,
    "W": 10,
    "I": null,
    "A": null,
    "Ld": null,
    "type": "Heavy Chariot"
  },
  {
    "unit": "War Wagon",
    "M": null,
    "WS": null,
    "BS": null,
    "S": 5,
    "T": 5,
    "W": 6,
    "I": null,
    "A": null,
    "Ld": null,
    "type": "Heavy Chariot"
  },
  {
    "unit": "Flagellant",
    "M": 4,
    "WS": 3,
    "BS": 2,
    "S": 3,
    "T": 3,
    "W": 1,
    "I": 3,
    "A": 1,
    "Ld": 5,
    "type": "Regular Infantry"
  },
  {
    "unit": "General of the Empire",
    "M": 4,
    "WS": 5,
    "BS": 5,
    "S": 4,
    "T": 4,
    "W": 3,
    "I": 5,
    "A": 3,
    "Ld": 10,
    "type": "Regular Infantry, Character"
  },
  {
    "unit": "Grand Master",
    "M": null,
    "WS": 6,
    "BS": 3,
    "S": 4,
    "T": 4,
    "W": 3,
    "I": 6,
    "A": 4,
    "Ld": 9,
    "type": "Heavy Cavalry, Character"
  },
  {
    "unit": "Great Cannon",
    "M": null,
    "WS": null,
    "BS": null,
    "S": null,
    "T": 6,
    "W": 3,
    "I": null,
    "A": null,
    "Ld": null,
    "type": "War Machine"
  },
  {
    "unit": "Griffon",
    "M": 6,
    "WS": 5,
    "BS": null,
    "S": 5,
    "T": 5,
    "W": 3,
    "I": 5,
    "A": 4,
    "Ld": null,
    "type": "Monstrous Creature"
  },
  {
    "unit": "Helblaster Volley Gun",
    "M": null,
    "WS": null,
    "BS": null,
    "S": null,
    "T": 6,
    "W": 3,
    "I": null,
    "A": null,
    "Ld": null,
    "type": "War Machine"
  },
  {
    "unit": "High Priest of Ulric",
    "M": 4,
    "WS": 5,
    "BS": 3,
    "S": 4,
    "T": 4,
    "W": 3,
    "I": 5,
    "A": 3,
    "Ld": 8,
    "type": "Regular Infantry, Character"
  },
  {
    "unit": "Imperial Ogre",
    "M": 6,
    "WS": 3,
    "BS": 3,
    "S": 4,
    "T": 4,
    "W": 3,
    "I": 2,
    "A": 3,
    "Ld": 7,
    "type": "Monstrous Infantry"
  },
  {
    "unit": "Inner Circle Knight",
    "M": null,
    "WS": 4,
    "BS": 3,
    "S": 4,
    "T": 3,
    "W": 1,
    "I": 4,
    "A": 1,
    "Ld": 9,
    "type": "Heavy Cavalry"
  },
  {
    "unit": "Lector of Sigmar",
    "M": 4,
    "WS": 5,
    "BS": 3,
    "S": 4,
    "T": 4,
    "W": 3,
    "I": 5,
    "A": 3,
    "Ld": 8,
    "type": "Regular Infantry, Character"
  },
  {
    "unit": "Outrider",
    "M": null,
    "WS": 3,
    "BS": 4,
    "S": 3,
    "T": 3,
    "W": 1,
    "I": 3,
    "A": 1,
    "Ld": 7,
    "type": "Light Cavalry"
  },
  {
    "unit": "Pegasus",
    "M": 8,
    "WS": 3,
    "BS": null,
    "S": 4,
    "T": 4,
    "W": 1,
    "I": 4,
    "A": 2,
    "Ld": null,
    "type": "Monstrous Cavalry"
  },
  {
    "unit": "Priest of Sigmar",
    "M": 4,
    "WS": 4,
    "BS": 3,
    "S": 4,
    "T": 4,
    "W": 2,
    "I": 4,
    "A": 2,
    "Ld": 7,
    "type": "Regular Infantry, Character"
  },
  {
    "unit": "Teutogen Guard",
    "M": 4,
    "WS": 4,
    "BS": 3,
    "S": 3,
    "T": 4,
    "W": 1,
    "I": 3,
    "A": 1,
    "Ld": 8,
    "type": "Heavy Infantry"
  },
  {
    "unit": "War Altar",
    "M": null,
    "WS": null,
    "BS": null,
    "S": 5,
    "T": 5,
    "W": 5,
    "I": null,
    "A": null,
    "Ld": null,
    "type": "Heavy Chariot"
  },
  {
    "unit": "Witch Hunter",
    "M": 4,
    "WS": 4,
    "BS": 4,
    "S": 4,
    "T": 4,
    "W": 2,
    "I": 5,
    "A": 2,
    "Ld": 8,
    "type": "Regular Infantry, Character"
  },
  {
    "unit": "Wizard Lord",
    "M": 4,
    "WS": 4,
    "BS": 3,
    "S": 3,
    "T": 4,
    "W": 3,
    "I": 3,
    "A": 2,
    "Ld": 8,
    "type": "Regular Infantry, Character"
  }
]
